markdown3_newtab/__init__.py
markdown_newtab/__init__.py
markdown3_newtab-0.2.0.dist-info/LICENSE
markdown3_newtab-0.2.0.dist-info/METADATA
markdown3_newtab-0.2.0.dist-info/WHEEL
markdown3_newtab-0.2.0.dist-info/top_level.txt
markdown3_newtab-0.2.0.dist-info/RECORD
