Metadata-Version: 2.1
Name: markdown3-newtab
Version: 0.2.0
Summary: Markdown Extension to add target="_blank" to all links.
Home-page: https://github.com/pehala/markdown-newtab
Author: Petr Hála
Author-email: halapetr@selfnet.cz
License: CC0
Platform: UNKNOWN
